[{"date":"2019-04-23","firstName":"floki","lastName":"netti","phonenumber":"5858385","tripID":5,"seats":2,"email":"emaillidfoka"},{"date":"2019-04-22","firstName":"egoijeg","lastName":"asdglsdg","phonenumber":"39023029835","tripID":4,"seats":2,"email":"sadglksdg"},{"date":"2019-05-02","firstName":"Fl처ki","lastName":"횧orleifsson","phonenumber":"8476889","tripID":8,"seats":6,"email":"flokith@outlook.com"},{"date":"2019-04-23","firstName":"Fl처ki","lastName":"횧orleifsson","phonenumber":"8476889","tripID":5,"seats":8,"email":"flokith@outlook.com"}]